moveread/pipelines/manual_select/__init__.py
moveread/pipelines/manual_select/__init__.pyi
moveread/pipelines/manual_select/main.py
moveread/pipelines/manual_select/types.py
moveread_pipelines_manual_select-0.1.9.dist-info/METADATA
moveread_pipelines_manual_select-0.1.9.dist-info/WHEEL
moveread_pipelines_manual_select-0.1.9.dist-info/top_level.txt
moveread_pipelines_manual_select-0.1.9.dist-info/RECORD
