Metadata-Version: 2.1
Name: moveread-pipelines-manual-select
Version: 0.1.9
Summary: Pipeline interface for manual grid selection
Author-email: Marcel Claramunt <marcel@moveread.com>
Project-URL: repo, https://github.com/moveread/REPO.git
Requires-Python: >=3.10
Requires-Dist: queue-api
Requires-Dist: pydantic ==2.*
Requires-Dist: moveread-annotations
Requires-Dist: moveread-boxes
Requires-Dist: lazy-loader
Requires-Dist: pipeteer
